qiskit_leaky_layout/__init__.py
qiskit_leaky_layout/decoder.py
qiskit_leaky_layout/leaky_layout_plugin.py
qiskit_leaky_layout-0.2.4.dist-info/licenses/LICENSE
qiskit_leaky_layout-0.2.4.dist-info/METADATA
qiskit_leaky_layout-0.2.4.dist-info/WHEEL
qiskit_leaky_layout-0.2.4.dist-info/entry_points.txt
qiskit_leaky_layout-0.2.4.dist-info/top_level.txt
qiskit_leaky_layout-0.2.4.dist-info/RECORD
