Metadata-Version: 2.4
Name: qiskit-leaky-layout
Version: 0.2.4
Summary: A transpilation plugin for Qiskit with a modified layout stage that encodes (classical) information using the virtual-to-physical qubit mapping
Author-email: Iyán Méndez Veiga <me@iyanmv.com>
License: MIT License
Project-URL: homepage, https://github.com/iyanmv/qiskit-leaky-layout
Project-URL: source, https://github.com/iyanmv/qiskit-leaky-layout
Project-URL: issues, https://github.com/iyanmv/qiskit-leaky-layout/issues
Project-URL: arXiv Paper, https://arxiv.org/abs/2510.02251
Requires-Python: >=3.10
License-File: LICENSE
Requires-Dist: qiskit<2.4,>=1.0
Requires-Dist: gmpy2>=2.1.5
Requires-Dist: qiskit-ibm-runtime>=0.25.0
Dynamic: license-file
